textfsm_jinja/__init__.py
textfsm_jinja/cli.py
textfsm_jinja/custom_functions.py
textfsm_jinja/gui.py
textfsm_jinja/parser.py
textfsm_jinja/processor.py
textfsm_jinja/renderer.py
textfsm_jinja/tests.py
textfsm_jinja-0.1.0.dist-info/licenses/LICENSE
textfsm_jinja-0.1.0.dist-info/METADATA
textfsm_jinja-0.1.0.dist-info/WHEEL
textfsm_jinja-0.1.0.dist-info/entry_points.txt
textfsm_jinja-0.1.0.dist-info/top_level.txt
textfsm_jinja-0.1.0.dist-info/RECORD
