Metadata-Version: 2.4
Name: textfsm-jinja
Version: 0.1.0
Summary: 一个基于TextFSM和Jinja2的文本解析和渲染库
Home-page: https://github.com/duanfu456/textfsm-jinja
Author: duanfu
Author-email: duanfu <duanfu456@163.com>
License: MIT
Project-URL: Homepage, https://github.com/duanfu456/textfsm-jinja
Project-URL: Repository, https://github.com/duanfu456/textfsm-jinja
Project-URL: Documentation, https://github.com/duanfu456/textfsm-jinja#readme
Classifier: Development Status :: 3 - Alpha
Classifier: Intended Audience :: Developers
Classifier: License :: OSI Approved :: MIT License
Classifier: Operating System :: OS Independent
Classifier: Programming Language :: Python :: 3
Classifier: Programming Language :: Python :: 3.7
Classifier: Programming Language :: Python :: 3.8
Classifier: Programming Language :: Python :: 3.9
Classifier: Programming Language :: Python :: 3.10
Requires-Python: >=3.7
License-File: LICENSE
Requires-Dist: textfsm
Requires-Dist: Jinja2
Provides-Extra: dev
Requires-Dist: pytest>=6.0; extra == "dev"
Requires-Dist: pytest-cov; extra == "dev"
Dynamic: author
Dynamic: home-page
Dynamic: license-file
Dynamic: requires-python
